llm_guard/__init__.py
llm_guard/main.py
py_llm_shield-1.0.1.dist-info/licenses/LICENSE MIT
py_llm_shield-1.0.1.dist-info/METADATA
py_llm_shield-1.0.1.dist-info/WHEEL
py_llm_shield-1.0.1.dist-info/top_level.txt
py_llm_shield-1.0.1.dist-info/RECORD
